.DS_Store
vapetool/__init__.py
vapetool/utils.py
vapetool-1.0.1.dist-info/LICENSE
vapetool-1.0.1.dist-info/METADATA
vapetool-1.0.1.dist-info/WHEEL
vapetool-1.0.1.dist-info/top_level.txt
vapetool-1.0.1.dist-info/RECORD
