Metadata-Version: 2.1
Name: vapetool
Version: 1.0.1
Summary: VapeTool python utils
Home-page: https://github.com/vape-tool/VapeTool-BatteriesParser
Author: Stanislaw Baranski
Author-email: stachu@stasbar.com
License: UNKNOWN
Platform: UNKNOWN
Classifier: Programming Language :: Python :: 3
Classifier: License :: OSI Approved :: MIT License
Classifier: Operating System :: OS Independent
